penguin_analyst_aviv/__init__.py
penguin_analyst_aviv-0.1.1.dist-info/METADATA
penguin_analyst_aviv-0.1.1.dist-info/WHEEL
penguin_analyst_aviv-0.1.1.dist-info/RECORD
