Metadata-Version: 2.1
Name: penguin-analyst-aviv
Version: 0.1.1
Summary: 
Author: avivlevit
Author-email: aviv.levit2909@gmail.com
Requires-Python: >=3.8,<4.0
Classifier: Programming Language :: Python :: 3
Classifier: Programming Language :: Python :: 3.8
Classifier: Programming Language :: Python :: 3.9
Classifier: Programming Language :: Python :: 3.10
Classifier: Programming Language :: Python :: 3.11
Requires-Dist: pandas (>=1.3.5,<2.0.0)
